pype_observe/__init__.py
pype_observe/event_handlers.py
pype_observe/metrics_service.py
pype_observe/observe.py
pype_observe/pype.py
pype_observe-1.0.0.dist-info/METADATA
pype_observe-1.0.0.dist-info/WHEEL
pype_observe-1.0.0.dist-info/top_level.txt
pype_observe-1.0.0.dist-info/RECORD
